openNPL/__init__.py
openNPL/asgi.py
openNPL/serializers.py
openNPL/settings.py
openNPL/urls.py
openNPL/views.py
openNPL/wsgi.py
openNPL-0.5.dist-info/LICENSE
openNPL-0.5.dist-info/METADATA
openNPL-0.5.dist-info/WHEEL
openNPL-0.5.dist-info/top_level.txt
openNPL-0.5.dist-info/RECORD
