Metadata-Version: 2.1
Name: openNPL
Version: 0.5
Summary: An open source platform for the management of non-performing loan portfolio data
Home-page: https://github.com/open-risk/openNPL
Author: Open Risk
Author-email: info@openrisk.eu
License: MIT
Keywords: credit,portfolio,loan,database
Platform: UNKNOWN
Classifier: Environment :: Web Environment
Classifier: Intended Audience :: Developers
Classifier: Intended Audience :: Science/Research
Classifier: Intended Audience :: Financial and Insurance Industry
Classifier: Development Status :: 3 - Alpha
Classifier: License :: OSI Approved :: Apache Software License
Classifier: Operating System :: OS Independent
Classifier: Programming Language :: Python :: 3 :: Only
Classifier: Programming Language :: Python :: 3.9
Classifier: Topic :: Scientific/Engineering
Classifier: Topic :: Scientific/Engineering :: Information Analysis
Provides: openNPL
Requires-Python: >=3.9
License-File: LICENSE
Requires-Dist: Django
